pyspark_connectby/__init__.py
pyspark_connectby/connectby_query.py
pyspark_connectby/dataframe_connectby.py
pyspark_connectby-1.1.3.dist-info/METADATA
pyspark_connectby-1.1.3.dist-info/WHEEL
pyspark_connectby-1.1.3.dist-info/RECORD
